LICENSE
LICENSE.fr
les_assets_generator/__init__.py
les_assets_generator/app/__init__.py
les_assets_generator/app/admin.py
les_assets_generator/app/apps.py
les_assets_generator/app/migrations/__init__.py
les_assets_generator/app/models.py
les_assets_generator/app/tests.py
les_assets_generator/app/urls.py
les_assets_generator/app/views.py
les_assets_generator/assets_generator/__init__.py
les_assets_generator/assets_generator/allauth.py
les_assets_generator/assets_generator/asgi.py
les_assets_generator/assets_generator/settings/__init__.py
les_assets_generator/assets_generator/settings/base.py
les_assets_generator/assets_generator/settings/dev.py
les_assets_generator/assets_generator/settings/production.py
les_assets_generator/assets_generator/urls.py
les_assets_generator/assets_generator/wsgi.py
les_assets_generator/locale/fr/LC_MESSAGES/django.po
les_assets_generator/manage.py
les_assets_generator/staticfiles/css/lyon_esport.css
les_assets_generator/staticfiles/img/logo/google.svg
les_assets_generator/templates/admin/login.html
les_assets_generator-0.6.0.dist-info/LICENSE.fr
les_assets_generator-0.6.0.dist-info/LICENSE
les_assets_generator-0.6.0.dist-info/WHEEL
les_assets_generator-0.6.0.dist-info/METADATA
les_assets_generator-0.6.0.dist-info/RECORD
