Metadata-Version: 2.1
Name: les-assets-generator
Version: 0.6.0
Summary: 
Home-page: https://github.com/lyon-esport/assets-generator
License: CeCILL
Keywords: django,esport,assets
Author: Ludovic Ortega
Author-email: ludovic.ortega@lyon-esport.fr
Requires-Python: >=3.8,<4.0
Classifier: License :: OSI Approved :: CEA CNRS Inria Logiciel Libre License, version 2.1 (CeCILL-2.1)
Classifier: License :: Other/Proprietary License
Classifier: Operating System :: OS Independent
Classifier: Programming Language :: Python
Classifier: Programming Language :: Python :: 3
Classifier: Programming Language :: Python :: 3.8
Classifier: Programming Language :: Python :: 3.9
Classifier: Programming Language :: Python :: 3.10
Classifier: Programming Language :: Python :: 3.10
Classifier: Programming Language :: Python :: 3.8
Classifier: Programming Language :: Python :: 3.9
Classifier: Topic :: Utilities
Requires-Dist: Django (>=4.0.6,<5.0.0)
Requires-Dist: Pillow (>=9.2.0,<10.0.0)
Requires-Dist: dj-database-url (>=1.0.0,<2.0.0)
Requires-Dist: django-allauth (>=0.51.0,<0.52.0)
Requires-Dist: django-colorfield (>=0.7.2,<0.8.0)
Requires-Dist: gunicorn (>=20.1.0,<21.0.0)
Requires-Dist: python-dotenv (>=0.20,<0.22)
Project-URL: Repository, https://github.com/lyon-esport/assets-generator
